mwdi/__init__.py
mwdi/mwdi.py
mwdi-0.72.dist-info/METADATA
mwdi-0.72.dist-info/WHEEL
mwdi-0.72.dist-info/top_level.txt
mwdi-0.72.dist-info/RECORD
