Metadata-Version: 2.1
Name: mwdi
Version: 0.72
Summary: Morlet Wave Damping Identification.
Home-page: https://github.com/ladisk/mwdi
Author: Ivan Tomac, Longqi Wang, Janko Slavič
Author-email: ivan.tomac@fs.uni-lj.si, janko.slavic@fs.uni-lj.si
Maintainer: Ivan Tomac, Janko Slavič
Maintainer-email: janko.slavic@fs.uni-lj.si
License: MIT license
Keywords: damping, morlet-wave, identification
Classifier: Development Status :: 3 - Alpha
Classifier: Intended Audience :: Developers
Classifier: Programming Language :: Python :: 3.8
Requires-Dist: numpy
Requires-Dist: scipy
Requires-Dist: pylint
Requires-Dist: pytest
